[
    {
        "name": "UnionBank",
        "description": "Lorem ipsum",
        "thumbnail": "https://placehold.co/800x400/png",
        "features": [
            {
                "icon": "icon1",
                "feature_title": "title1"
            },
            {
                "icon": "icon2",
                "feature_title": "title2"
            },
            {
                "icon": "icon1",
                "feature_title": "title3"
            }
        ],
        "techstack": [
            "React",
            "Redux",
            "AntD",
            "Bootstrap",
            "Rest API"
        ],
        "tech_position": "Lorem Ipsum"
    },
    {
        "name": "UnionBank",
        "description": "Lorem ipsum",
        "thumbnail": "https://placehold.co/800x400/png",
        "features": [
            {
                "icon": "icon1",
                "feature_title": "title1"
            },
            {
                "icon": "icon2",
                "feature_title": "title2"
            },
            {
                "icon": "icon1",
                "feature_title": "title3"
            }
        ],
        "techstack": [
            "React",
            "Redux",
            "AntD",
            "Bootstrap",
            "Rest API"
        ],
        "tech_position": "Lorem Ipsum"
    },
    {
        "name": "UnionBank",
        "description": "Lorem ipsum",
        "thumbnail": "https://placehold.co/800x400/png",
        "features": [
            {
                "icon": "icon1",
                "feature_title": "title1"
            },
            {
                "icon": "icon2",
                "feature_title": "title2"
            },
            {
                "icon": "icon1",
                "feature_title": "title3"
            }
        ],
        "techstack": [
            "React",
            "Redux",
            "AntD",
            "Bootstrap",
            "Rest API"
        ],
        "tech_position": "Lorem Ipsum"
    }
]